jdeskew/__init__.py
jdeskew/estimator.py
jdeskew/utility.py
jdeskew-0.3.0.dist-info/licenses/LICENSE
jdeskew-0.3.0.dist-info/METADATA
jdeskew-0.3.0.dist-info/WHEEL
jdeskew-0.3.0.dist-info/top_level.txt
jdeskew-0.3.0.dist-info/RECORD
