Metadata-Version: 2.4
Name: jdeskew
Version: 0.3.0
Summary: Document Image Skew Estimation using Adaptive Radial Projection
Author-email: Luan Pham <phamquiluan@gmail.com>
License: MIT License
License-File: LICENSE
Requires-Dist: numpy
Requires-Dist: opencv-python-headless
Provides-Extra: dev
Requires-Dist: black; extra == "dev"
Requires-Dist: pytest; extra == "dev"
Requires-Dist: coverage; extra == "dev"
Requires-Dist: pre-commit; extra == "dev"
Requires-Dist: pytest-xdist; extra == "dev"
Requires-Dist: fastapi; extra == "dev"
Requires-Dist: uvicorn[standard]; extra == "dev"
Requires-Dist: python-multipart; extra == "dev"
Dynamic: license-file
